extended_knapsack/__init__.py
extended_knapsack/knapsack.py
extended_knapsack-0.0.1.dist-info/LICENSE
extended_knapsack-0.0.1.dist-info/METADATA
extended_knapsack-0.0.1.dist-info/WHEEL
extended_knapsack-0.0.1.dist-info/top_level.txt
extended_knapsack-0.0.1.dist-info/RECORD
