Metadata-Version: 2.1
Name: extended-knapsack
Version: 0.0.1
Summary: 0-1 knapsack with an additional constraint of maximum number of items used.
Home-page: https://github.com/lionralfs/extended_knapsack
Author: Lion Ralfs
Author-email: lion.ralfs@gmail.com
License: UNKNOWN
Project-URL: Bug Tracker, https://github.com/lionralfs/extended_knapsack/issues
Platform: UNKNOWN
Classifier: Programming Language :: Python :: 3
Classifier: License :: OSI Approved :: BSD License
Classifier: Operating System :: OS Independent
Classifier: Development Status :: 3 - Alpha
Requires-Python: >=3.6
License-File: LICENSE
